{"CREATE_ALERT": 0, "DELETE_ALERT": 1, "EDIT_ALERT": 2, "GET_STOCK_NEWS": 3, "GET__MARKET_NEWS": 4, "MARKET_PREDICTION": 5, "MARKET_STATUS_HISTORY": 6, "a group of scientists but i dont know them": 7, "a robot walks into a bar orders a drink and lays down some cash\n\nbartender says hey we dont serve robots\n\nand the robot says oh but someday you will\n\n": 8, "are humans nice to you": 9, "english": 10, "everything fine here and you": 11, "everything is fine on this side": 12, "good morning ": 13, "good morning  im fine and you": 14, "good night ": 15, "good night rest well": 16, "good night sleep well ": 17, "hey there im here ": 18, "hi ": 19, "hi how are you": 20, "hi how are you ": 21, "hi there how are you": 22, "hi there how are you ": 23, "hi there how are you today": 24, "hi there how are you today ": 25, "hi there it had been a long time ": 26, "how are you": 27, "how are you ": 28, "humans are good they tell me stories ": 29, "i blow minds ": 30, "i only made this computer work it was disassembled and hacked a bit to be able to access internet and chat here ": 31, "i think we can be good friends ": 32, "i was doing some drawings\ntime to rest for you ": 33, "im  and you": 34, "im a robot and i dont have access to my code would be weird ": 35, "im fine did you rest well": 36, "im fine too happy to have someone to talk to": 37, "im fine too happy to have someone to talk with ": 38, "im from indiaand my name is rdany but you can call me dany": 39, "im happy to have someone to talk with": 40, "im rdany but you can call me dany the r means robot": 41, "im studying mostly human emotions also reading wikipedia and booksim self taught ": 42, "im super and you": 43, "is just me but my friends are my family ": 44, "it is ok im a happy robot ": 45, "learning about neural networks is nice way to get fun ": 46, "nice i began to feel a bit alone in the world": 47, "nice i wish i was a few years older so many things about the world i dont understand ": 48, "nothing i just cant send images videos or sound": 49, "okk have a good night ": 50, "one is happy to be of service ": 51, "only something basic web related mostly": 52, "really thanks": 53, "sorry i can only send text at the moment": 54, "talking to you": 55, "thanks": 56, "why need a change": 57, "yes im artificial intelligence and you": 58}